clep/__init__.py
clep/__main__.py
clep/cli.py
clep/constants.py
clep/classification/__init__.py
clep/classification/hpo.py
clep/classification/utils.py
clep/embedding/__init__.py
clep/embedding/evaluate.py
clep/embedding/kge.py
clep/embedding/network_generator.py
clep/sample_scoring/__init__.py
clep/sample_scoring/limma.py
clep/sample_scoring/radical_search.py
clep/sample_scoring/ssgsea.py
clep/sample_scoring/z_score.py
clep-0.0.6.dist-info/licenses/AUTHORS.md
clep-0.0.6.dist-info/licenses/LICENSE
clep-0.0.6.dist-info/METADATA
clep-0.0.6.dist-info/WHEEL
clep-0.0.6.dist-info/entry_points.txt
clep-0.0.6.dist-info/top_level.txt
clep-0.0.6.dist-info/RECORD
