Metadata-Version: 2.4
Name: clep
Version: 0.0.6
Summary: A Hybrid Data and Knowledge Driven Framework for Generating Patient Representations
Author-email: Vinay Bharadhwaj <vinay.srinivas.bharadhwaj@scai.fraunhofer.de>
License:                                  Apache License
Keywords: Bioinformatics,Machine Learning,Prediction Models,Embeddings
Classifier: Development Status :: 4 - Beta
Classifier: Environment :: Console
Classifier: Intended Audience :: Developers
Classifier: Intended Audience :: Science/Research
Classifier: License :: OSI Approved :: Apache Software License
Classifier: Operating System :: OS Independent
Classifier: Programming Language :: Python
Classifier: Programming Language :: Python :: 3.7
Classifier: Programming Language :: Python :: 3.12
Classifier: Programming Language :: Python :: 3 :: Only
Classifier: Topic :: Scientific/Engineering :: Bio-Informatics
Requires-Python: >=3.7
License-File: LICENSE
License-File: AUTHORS.md
Requires-Dist: click==8.1.7
Requires-Dist: pandas==2.2.2
Requires-Dist: rpy2==3.5.15
Requires-Dist: statsmodels==0.14.1
Requires-Dist: scikit-learn==1.5.0
Requires-Dist: seaborn==0.13.2
Requires-Dist: gseapy==1.1.2
Requires-Dist: cffi==1.16.0
Requires-Dist: pycairo==1.26.0
Requires-Dist: networkx==3.3
Requires-Dist: xgboost==2.0.3
Requires-Dist: tqdm==4.66.4
Requires-Dist: pykeen==1.11.1
Requires-Dist: pandera==0.19.1
Requires-Dist: optuna==3.6.1
Requires-Dist: joblib==1.4.2
Requires-Dist: sqlalchemy==2.0.30
Requires-Dist: mysqlclient==2.2.4
Requires-Dist: scipy==1.15.3
Provides-Extra: docs
Requires-Dist: sphinx; extra == "docs"
Requires-Dist: sphinx-rtd-theme; extra == "docs"
Requires-Dist: sphinx-click; extra == "docs"
Requires-Dist: sphinx-autodoc-typehints; extra == "docs"
Provides-Extra: dev
Requires-Dist: black; extra == "dev"
Requires-Dist: mypy; extra == "dev"
Requires-Dist: bump-my-version; extra == "dev"
Requires-Dist: pandas-stubs; extra == "dev"
Dynamic: license-file
